{
  "cv_results": [
    {
      "fold": 0,
      "best_epoch": 14,
      "f1": 0.9142857142857143,
      "balanced_accuracy": 0.845989926385122,
      "auc": 0.8930647036032546,
      "confusion_matrix": [
        [
          23,
          6
        ],
        [
          9,
          80
        ]
      ]
    },
    {
      "fold": 1,
      "best_epoch": 14,
      "f1": 0.9259259259259259,
      "balanced_accuracy": 0.6363636363636364,
      "auc": 0.79,
      "confusion_matrix": [
        [
          6,
          16
        ],
        [
          0,
          100
        ]
      ]
    },
    {
      "fold": 2,
      "best_epoch": 0,
      "f1": 0.8648648648648649,
      "balanced_accuracy": 0.587719298245614,
      "auc": 0.7894736842105263,
      "confusion_matrix": [
        [
          1,
          2
        ],
        [
          3,
          16
        ]
      ]
    },
    {
      "fold": 3,
      "best_epoch": 0,
      "f1": 0.0,
      "balanced_accuracy": 0.4772727272727273,
      "auc": 0.6056818181818182,
      "confusion_matrix": [
        [
          21,
          1
        ],
        [
          40,
          0
        ]
      ]
    },
    {
      "fold": 4,
      "best_epoch": 16,
      "f1": 0.8603351955307262,
      "balanced_accuracy": 0.6145833333333334,
      "auc": 0.7779166666666666,
      "confusion_matrix": [
        [
          8,
          22
        ],
        [
          3,
          77
        ]
      ]
    }
  ],
  "test_results": {
    "f1": 0.8153846153846154,
    "balanced_accuracy": 0.6422558922558923,
    "auc": 0.7003367003367004,
    "confusion_matrix": [
      [
        10,
        23
      ],
      [
        1,
        53
      ]
    ],
    "classification_report": {
      "0": {
        "precision": 0.9090909090909091,
        "recall": 0.30303030303030304,
        "f1-score": 0.45454545454545453,
        "support": 33.0
      },
      "1": {
        "precision": 0.6973684210526315,
        "recall": 0.9814814814814815,
        "f1-score": 0.8153846153846154,
        "support": 54.0
      },
      "accuracy": 0.7241379310344828,
      "macro avg": {
        "precision": 0.8032296650717703,
        "recall": 0.6422558922558923,
        "f1-score": 0.634965034965035,
        "support": 87.0
      },
      "weighted avg": {
        "precision": 0.7776769509981851,
        "recall": 0.7241379310344828,
        "f1-score": 0.6785145888594164,
        "support": 87.0
      }
    },
    "best_epoch": 20,
    "es_holdout_auc": 0.8181818181818181
  },
  "cv_mean_f1": 0.7130823401214463,
  "cv_std_f1": 0.3574892870646465,
  "cv_mean_auc": 0.7712273745324532,
  "cv_std_auc": 0.09271434829153231,
  "model_params": {
    "epochs": 50,
    "batch_size": 32,
    "learning_rate": 0.0005,
    "dropout": 0.3,
    "weight_decay": 0.0001,
    "patience": 15
  },
  "n_features": 10000,
  "test_predictions": {
    "y_true": [
      1,
      1,
      1,
      0,
      1,
      1,
      1,
      1,
      1,
      1,
      1,
      1,
      1,
      0,
      1,
      1,
      1,
      1,
      1,
      1,
      1,
      1,
      1,
      1,
      1,
      0,
      0,
      1,
      1,
      0,
      1,
      0,
      1,
      0,
      0,
      0,
      0,
      1,
      0,
      1,
      0,
      1,
      0,
      0,
      0,
      1,
      0,
      1,
      1,
      1,
      0,
      1,
      1,
      1,
      1,
      1,
      0,
      1,
      0,
      0,
      1,
      1,
      1,
      1,
      0,
      1,
      0,
      0,
      1,
      1,
      0,
      1,
      1,
      1,
      0,
      1,
      1,
      0,
      0,
      0,
      0,
      0,
      1,
      0,
      0,
      0,
      1
    ],
    "y_pred": [
      1,
      1,
      1,
      1,
      1,
      1,
      1,
      1,
      1,
      1,
      1,
      1,
      0,
      0,
      1,
      1,
      1,
      1,
      1,
      1,
      1,
      1,
      1,
      1,
      1,
      1,
      1,
      1,
      1,
      1,
      1,
      0,
      1,
      0,
      0,
      0,
      1,
      1,
      0,
      1,
      1,
      1,
      1,
      1,
      1,
      1,
      0,
      1,
      1,
      1,
      1,
      1,
      1,
      1,
      1,
      1,
      0,
      1,
      1,
      1,
      1,
      1,
      1,
      1,
      1,
      1,
      1,
      1,
      1,
      1,
      1,
      1,
      1,
      1,
      1,
      1,
      1,
      0,
      0,
      1,
      1,
      1,
      1,
      1,
      1,
      1,
      1
    ],
    "y_proba": [
      0.9259323477745056,
      0.987841784954071,
      0.9921566247940063,
      0.9842010140419006,
      0.992828905582428,
      0.9870243072509766,
      0.974762499332428,
      0.9999991655349731,
      0.9874383807182312,
      0.9756472110748291,
      0.9866408705711365,
      0.9999626874923706,
      0.30876624584198,
      0.017490332946181297,
      0.9346653819084167,
      0.9719948172569275,
      0.6488262414932251,
      0.9968879818916321,
      0.9880734086036682,
      0.9857694506645203,
      0.9851552844047546,
      0.883676290512085,
      0.9858489036560059,
      0.9930670261383057,
      0.9877089262008667,
      0.5635606646537781,
      0.9907135963439941,
      0.9539825320243835,
      0.9797490239143372,
      0.9832210540771484,
      0.9460648894309998,
      0.3073045015335083,
      0.9852264523506165,
      0.21459951996803284,
      0.03880270943045616,
      0.14614619314670563,
      0.9876900911331177,
      0.9900072813034058,
      0.19071143865585327,
      0.9875351190567017,
      0.9316897988319397,
      0.9886416792869568,
      0.9897032380104065,
      0.9745504856109619,
      0.9496335387229919,
      0.5203505754470825,
      0.1664097011089325,
      0.9900789260864258,
      0.9615218639373779,
      0.9893997311592102,
      0.9879360198974609,
      0.9823960065841675,
      0.9895920157432556,
      0.9615201950073242,
      0.9823488593101501,
      0.9861297011375427,
      0.3442460000514984,
      0.9835671186447144,
      0.99286288022995,
      0.9902637004852295,
      0.9843695163726807,
      0.9896426796913147,
      0.9868664741516113,
      0.9960556030273438,
      0.7674120664596558,
      0.9699655175209045,
      0.9243669509887695,
      0.990809440612793,
      0.9792925119400024,
      0.9965452551841736,
      0.9605610966682434,
      0.9854112863540649,
      0.9857265949249268,
      0.9972231388092041,
      0.9903165698051453,
      0.9859715104103088,
      0.9924806356430054,
      0.08878645300865173,
      0.04967544972896576,
      0.9521494507789612,
      0.9634981751441956,
      0.6479707956314087,
      0.99652099609375,
      0.9969504475593567,
      0.9068966507911682,
      0.9983453750610352,
      0.9854705333709717
    ]
  },
  "feature_importance_top20": {
    "indices": [
      2552,
      4889,
      8201,
      771,
      2546,
      3694,
      4991,
      2551,
      9464,
      8526,
      8979,
      6267,
      4886,
      9330,
      7100,
      7105,
      8525,
      2549,
      6916,
      2548
    ],
    "scores": [
      0.004447357263416052,
      0.00446404330432415,
      0.0044698636047542095,
      0.004488199949264526,
      0.0044928197748959064,
      0.004505872260779142,
      0.004534819163382053,
      0.004569484386593103,
      0.00458422489464283,
      0.004674325697124004,
      0.004789211321622133,
      0.004827635828405619,
      0.004933279473334551,
      0.004984219558537006,
      0.005042751785367727,
      0.005100097041577101,
      0.005620836745947599,
      0.0060061803087592125,
      0.006081236060708761,
      0.007283344864845276
    ],
    "kmers": [
      "GCTGCTGGAAG",
      "CAGCCAGCCGC",
      "GCGCTGCGCCT",
      "GCAGCTGGCGG",
      "CAGCGACAGGC",
      "CCAGCGCCGCC",
      "ATTGCCGCCGG",
      "CGCTGCTGGAA",
      "CGCCAGCGTTT",
      "GCTGGGGGTGA",
      "TCCTGCCGCTG",
      "CGCTGGTCACC",
      "CGATACCGGCG",
      "CCAGCGGCCAT",
      "CTGCGCCAGTT",
      "TTCCGCCAGCC",
      "TGATTATCGCC",
      "CCGGTGGCGCT",
      "ATCACCGCGCT",
      "CCCGGTGGCGC"
    ]
  }
}